url2llm/__init__.py
url2llm/cli.py
url2llm-0.3.3.dist-info/licenses/LICENSE
url2llm-0.3.3.dist-info/METADATA
url2llm-0.3.3.dist-info/WHEEL
url2llm-0.3.3.dist-info/entry_points.txt
url2llm-0.3.3.dist-info/top_level.txt
url2llm-0.3.3.dist-info/RECORD
