Metadata-Version: 2.4
Name: url2llm
Version: 0.3.3
Summary: The easiest way to crawl a website and produce LLM ready markdown files
License-Expression: MIT
Project-URL: Homepage, https://github.com/diegobit/url2llm
Requires-Python: >=3.12
License-File: LICENSE
Requires-Dist: crawl4ai<0.7
Requires-Dist: fire>=0.7.0
Dynamic: license-file
